lcax-3.3.0.dist-info/METADATA
lcax-3.3.0.dist-info/WHEEL
lcax-3.3.0.dist-info/licenses/LICENSE
lcax/__init__.py
lcax/lcax.abi3.so
lcax/lcax.pyi
lcax-3.3.0.dist-info/RECORD
