Metadata-Version: 2.4
Name: lcax
Version: 3.3.0
Requires-Dist: cffi
Requires-Dist: pytest ; extra == 'tests'
Requires-Dist: pytest-datafixtures ; extra == 'tests'
Provides-Extra: tests
License-File: LICENSE
License-File: LICENSE
Summary: LCAx is an open, machine and human-readable data format for exchanging LCA results.
Home-Page: https://lcax.kongsgaard.eu
Author-email: Christian Kongsgaard <christian@kongsgaard.eu>
Requires-Python: >=3.10
Project-URL: homepage, https://lcax.kongsgaard.eu
Project-URL: documentation, https://lcax.kongsgaard.eu
Project-URL: repository, https://github.com/ocni-dtu/lcax
